guardian1/__init__.py
guardian1/core.py
guardian1/utils.py
no2_2exit-1.0.dist-info/METADATA
no2_2exit-1.0.dist-info/WHEEL
no2_2exit-1.0.dist-info/top_level.txt
no2_2exit-1.0.dist-info/RECORD
