Metadata-Version: 2.4
Name: NO2_2EXIT
Version: 1.0
Summary: Instagram info library
Author: ITSH
Requires-Dist: requests
Requires-Dist: instaloader
Dynamic: author
Dynamic: requires-dist
Dynamic: summary
